{
  "parent": "minecraft:recipes/root",
  "criteria": {
    "has_the_recipe": {
      "conditions": {
        "recipe": "powerful_sauces:augmented_mustard"
      },
      "trigger": "minecraft:recipe_unlocked"
    },
    "powerful_sauces:has_item": {
      "conditions": {
        "items": [
          {
            "items": [
              "powerful_sauces:mustard"
            ]
          }
        ]
      },
      "trigger": "minecraft:inventory_changed"
    }
  },
  "requirements": [
    [
      "powerful_sauces:has_item",
      "has_the_recipe"
    ]
  ],
  "rewards": {
    "recipes": [
      "powerful_sauces:augmented_mustard"
    ]
  },
  "sends_telemetry_event": false
}